<?xml version="1.0" encoding="utf-8"?>
<notchscreen_whitelist>
  <none_notch_app_hide name="ScreenRecorder"/>
  <none_notch_app_hide name="HwGlobalActions"/>
  <none_notch_app_hide name="com.taobao.taobao/taobao.tao.detail.activity.DetailActivity"/>
  <none_notch_app_hide name="com.achievo.vipshop/com.achievo.vipshop.productdetail.activity.NewProductDetailActivity"/>
  <none_notch_app_hide name="com.anjuke.android.app/com.anjuke.android.app.newhouse.newhouse.activity.BuildingDetailActivity"/>
  <none_notch_app_hide name="com.autohome.mycar/com.autohome.mycar.module.main.MainActivity"/>
  <none_notch_app_hide name="com.xunmeng.pinduoduo/com.xunmeng.pinduoduo.activity.NewPageActivity"/>
  <none_notch_app_hide name="com.ss.android.essay.joke/com.ss.android.essay.base.channel.ui.ChannelActivity"/>
  <none_notch_app_hide name="com.meitu.meipaimv/com.meitu.meipaimv.community.main.MainActivity"/>
  <none_notch_app_hide name="com.xiachufang/com.xiachufang.activity.columns.ColumnPreviewActivity"/>
  <none_notch_app_hide name="com.gotokeep.keep/com.gotokeep.keep.activity.training.collection.TrainCollectionActivity"/>
  <none_notch_app_hide name="com.tencent.qt.qtl/com.tencent.qt.qtl.activity.videocenter.VideoDetailPlayActivity"/>
  <none_notch_app_hide name="com.fenbi.android.solar/com.yuantiku.android.common.yuandaily.activity.YuandailyDetailActivity"/>
  <none_notch_app_hide name="com.lphtsccft/com.lphtsccft.zhangle.main.MainActivity"/>
  <none_notch_app_hide name="com.fanli.android.apps/com.fanli.android.module.main.activity.PanoMainActivity"/>
  <none_notch_app_hide name="com.flightmanager.view/com.flightmanager.view.Main"/>
  <none_notch_app_hide name="com.dw.btime/com.dw.btime.MainTabActivity"/>
  <none_notch_app_hide name="com.dw.btime/com.dw.btime.mall.MallMommyBuyItemDetailActivity"/>
  <none_notch_app_hide name="com.paic.zhifu.wallet.activity/com.paic.zhifu.wallet.activity.modules.homev4.YiqianbaoActivity"/>
  <none_notch_app_hide name="com.mfw.roadbook/com.mfw.roadbook.main.MainActivity"/>
  <none_notch_app_hide name="com.mfw.roadbook/com.mfw.roadbook.web.WebViewActivity"/>
  <none_notch_app_hide name="com.mfw.roadbook/com.mfw.roadbook.travelguide.articlerecord.TravelArticleWebViewActivity"/>
  <none_notch_app_hide name="com.soft.blued/com.soft.blued.ui.live.activity.PlayingOnliveActivity"/>
  <none_notch_app_hide name="com.csair.mbp/com.csair.mbp.CSMBPActivity"/>
  <none_notch_app_hide name="com.jingdong.pdj/pdj.main.MainActivity"/>
  <none_notch_app_hide name="com.jingdong.pdj/main.csdj.activity.CommodityActivity"/>
  <none_notch_app_hide name="com.balance6game.housingfund/com.balance6game.housingfund.activity.MainActivity"/>
  <none_notch_app_hide name="com.taobao.taobao/com.taobao.tao.detail.activity.DetailActivity"/>
  <none_notch_app_hide name="com.taobao.ju.android/com.taobao.ju.android.detail.activity.ItemDetailActivity"/>
  <none_notch_app_hide name="com.babytree.apps.lama/com.babytree.apps.time.common.MainActivity"/>
  <none_notch_app_hide name="com.u17.comic.phone/com.u17.comic.phone.activitys.ComicDetailActivity"/>
  <none_notch_app_hide name="cn.ibuka.manga.ui/cn.ibuka.manga.md.activity.ActivityMain"/>
  <none_notch_app_hide name="com.zhejiangdaily/com.daily.news.launcher.MainActivity"/>
  <none_notch_app_hide name="com.lejent.zuoyeshenqi.afanti/com.lejent.zuoyeshenqi.afanti.activity.MainActivity"/>
  <none_notch_app_hide name="com.tal.kaoyan/com.tal.kaoyan.ui.activity.HomeTabActivity"/>
  <none_notch_app_hide name="com.nanyiku/com.nanyiku.activitys.main.MainActivity"/>
  <none_notch_app_hide name="cmccwm.mobilemusic/cmccwm.mobilemusic.renascence.ui.activity.SingerMainPageActivity"/>
  <none_notch_app_hide name="cmccwm.mobilemusic/cmccwm.mobilemusic.renascence.ui.activity.MusicanSingleSongActivity"/>
  <none_notch_app_hide name="cmccwm.mobilemusic/cmccwm.mobilemusic.videoplayer.mv.VideoPlayerActivity"/>
  <none_notch_app_hide name="cmccwm.mobilemusic/cmccwm.mobilemusic.videoplayer.concert.ConcertPlayActivity"/>
  <none_notch_app_hide name="com.sankuai.meituan/com.meituan.android.hotel.reuse.detail.HotelPoiDetailActivity"/>
  <none_notch_app_hide name="cn.kuwo.player/cn.kuwo.player.activities.MainActivity"/>
  <none_notch_app_hide name="com.netease.cloudmusic/com.netease.cloudmusic.activity.RadioDetailActivity"/>
  <none_notch_app_hide name="com.yipiao/com.zt.hotel.activity.HotelDetailActivity"/>
  <none_notch_app_hide name="com.greenpoint.android.mc10086.activity/com.leadeon.cmcc.base.StartPageActivity"/>
  <none_notch_app_hide name="com.gotokeep.keep/com.gotokeep.keep.activity.store.GoodsDetailActivity"/>
  <none_notch_app_hide name="com.gotokeep.keep.activity.community.HashTagWebviewActivity"/>
  <none_notch_app_hide name="com.gotokeep.keep/com.gotokeep.keep.refactor.business.bootcamp.activity.CreateBootCampActivity"/>
  <none_notch_app_hide name="com.baidu.yuedu/com.baidu.bdreader.ui.BDReaderActivity"/>
  <none_notch_app_hide name="com.chaozh.iReaderFree/com.zhangyue.iReader.read.ui.Activity_BookBrowser_TXT"/>
  <none_notch_app_hide name="cn.jj/cn.jj.mobile.lobby.view.Main"/>
  <none_notch_app_hide name="com.youloft.calendar/com.youloft.calendar.WebActivity"/>
  <none_notch_app_hide name="com.youloft.calendar/com.youloft.calendar.StarWebActivity"/>
  <none_notch_app_hide_fold name="com.qiyi.video/org.iqiyi.video.activity.PlayerActivity"/>
  <none_notch_app_hide_fold name="com.tencent.qqlive/com.tencent.qqlive.ona.activity.VideoDetailActivity"/>
  <none_notch_app_hide_fold name="com.ss.android.article.video/com.ss.android.article.video.activity.SplashActivity"/>
  <system_app name="com.hihonor.camera"/>
  <system_app name="com.hihonor.hifolder"/>
  <system_app name="com.android.cts.priv.ctsshim"/>
  <system_app name="com.hihonor.tips"/>
  <system_app name="com.hihonor.android.launcher"/>
  <system_app name="com.android.mediacenter"/>
  <system_app name="com.android.phone.recorder"/>
  <system_app name="com.android.providers.calendar"/>
  <system_app name="com.hihonor.health"/>
  <system_app name="com.hihonor.hidisk"/>
  <system_app name="com.hihonor.hiview"/>
  <system_app name="com.hihonor.bluetooth"/>
  <system_app name="com.android.providers.media"/>
  <system_app name="com.hihonor.android.thememanager"/>
  <system_app name="com.android.wallpapercropper"/>
  <system_app name="com.hihonor.android.FloatTasks"/>
  <system_app name="com.hihonor.desktop.systemui"/>
  <system_app name="com.hihonor.intelligent"/>
  <system_app name="com.hihonor.motionservice"/>
  <system_app name="com.hihonor.appmarket"/>
  <system_app name="com.hihonor.parentcontrol"/>
  <system_app name="com.android.documentsui"/>
  <system_app name="com.android.htmlviewer"/>
  <system_app name="com.android.companiondevicemanager"/>
  <system_app name="com.hihonor.wallet"/>
  <system_app name="com.hihonor.android.totemweather"/>
  <system_app name="com.hihonor.android.totemweather"/>
  <system_app name="com.android.providers.downloads"/>
  <system_app name="com.hihonor.android.findmyphone"/>
  <system_app name="com.hihonor.trustcircle"/>
  <system_app name="com.realvnc.android.remote"/>
  <system_app name="com.hihonor.phoneservice"/>
  <system_app name="com.hihonor.desktop.explorer"/>
  <system_app name="com.hihonor.screenrecorder"/>
  <system_app name="com.hihonor.videoeditor"/>
  <system_app name="com.hihonor.securitymgr"/>
  <system_app name="com.android.browser"/>
  <system_app name="com.android.soundrecorder"/>
  <system_app name="com.hihonor.iconnect"/>
  <system_app name="com.hihonor.android.AutoRegSms"/>
  <system_app name="com.hihonor.koBackup"/>
  <system_app name="com.hihonor.hiviewtunnel"/>
  <system_app name="com.android.providers.downloads.ui"/>
  <system_app name="com.android.vending"/>
  <system_app name="com.hihonor.smarthome"/>
  <system_app name="com.hihonor.vrinstaller"/>
  <system_app name="com.baidu.input_hihonor"/>
  <system_app name="com.stupeflix.replay"/>
  <system_app name="com.android.certinstaller"/>
  <system_app name="com.google.android.marvin.talkback"/>
  <system_app name="com.hihonor.imedia.sws"/>
  <system_app name="com.honor.club"/>
  <system_app name="com.hihonor.hwid"/>
  <system_app name="com.android.contacts"/>
  <system_app name="com.hihonor.mms"/>
  <system_app name="com.android.mtp"/>
  <system_app name="com.android.nfc"/>
  <system_app name="com.android.stk"/>
  <system_app name="com.android.backupconfirm"/>
  <system_app name="com.hihonor.android.instantshare"/>
  <system_app name="com.hihonor.trustagent"/>
  <system_app name="com.hihonor.trustspace"/>
  <system_app name="com.hihonor.indexsearch"/>
  <system_app name="com.hihonor.android.internal.app"/>
  <system_app name="com.hihonor.gamebox"/>
  <system_app name="com.hihonor.hwasm"/>
  <system_app name="com.hihonor.lives"/>
  <system_app name="com.android.calendar"/>
  <system_app name="com.android.printspooler"/>
  <system_app name="com.android.incallui"/>
  <system_app name="com.hihonor.systemmanager"/>
  <system_app name="com.hihonor.nb.service"/>
  <system_app name="com.hihonor.yellowpage"/>
  <system_app name="com.android.bips"/>
  <system_app name="com.android.honor.projectmenu"/>
  <system_app name="com.hihonor.android.clone"/>
  <system_app name="com.google.android.webview"/>
  <system_app name="com.hihonor.HnMultiScreenShot"/>
  <system_app name="com.hihonor.vassistant"/>
  <system_app name="com.android.server.telecom"/>
  <system_app name="com.example.android.notepad"/>
  <system_app name="com.android.keychain"/>
  <system_app name="com.android.keyguard"/>
  <system_app name="com.hihonor.languagedownloader"/>
  <system_app name="com.android.gallery3d"/>
  <system_app name="com.google.android.gsf"/>
  <system_app name="com.google.android.partnersetup"/>
  <system_app name="com.hihonor.fido.uafclient"/>
  <system_app name="com.android.packageinstaller"/>
  <system_app name="com.hihonor.hwireader"/>
  <system_app name="com.hihonor.android.mirrorshare"/>
  <system_app name="com.hihonor.contactscamcard"/>
  <system_app name="com.hihonor.security"/>
  <system_app name="com.android.managedprovisioning"/>
  <system_app name="com.hihonor.hitouch"/>
  <system_app name="com.hihonor.compass"/>
  <system_app name="com.android.dreams.phototable"/>
  <system_app name="com.hihonor.vrservice"/>
  <system_app name="com.hihonor.android.dsdscardmanager"/>
  <system_app name="com.hihonor.ouc"/>
  <system_app name="com.hihonor.android.hwpay"/>
  <system_app name="com.hihonor.android.wfdft"/>
  <system_app name="com.android.wallpaper.livepicker"/>
  <system_app name="com.android.apps.tag"/>
  <system_app name="com.android.storagemanager"/>
  <system_app name="com.android.settings"/>
  <system_app name="com.hihonor.vmall"/>
  <system_app name="com.android.calculator2"/>
  <system_app name="com.qeexo.smartshot"/>
  <system_app name="com.svox.pico"/>
  <system_app name="org.simalliance.openmobileapi.service"/>
  <system_app name="com.hihonor.android.projectmenu"/>
  <system_app name="com.hihonor.android.totemweatherapp"/>
  <system_app name="com.android.cts.ctsshim"/>
  <system_app name="com.hihonor.android.remotecontroller"/>
  <system_app name="com.hihonor.android.pushagent"/>
  <system_app name="com.hihonor.betaclub"/>
  <system_app name="com.android.vpndialogs"/>
  <system_app name="com.android.email"/>
  <system_app name="com.android.phone"/>
  <system_app name="com.android.shell"/>
  <system_app name="com.android.emergency"/>
  <system_app name="com.hihonor.scanner"/>
  <system_app name="com.android.deskclock"/>
  <system_app name="com.android.systemui"/>
  <system_app name="com.android.exchange"/>
  <system_app name="com.hihonor.hwdetectrepair"/>
  <system_app name="com.hihonor.hwusbearphoneupdate"/>
  <system_app name="com.hihonor.skytone"/>
  <system_app name="com.hihonor.hiskytone"/>
  <system_app name="com.hihonor.aod"/>
  <system_app name="com.hihonor.ims"/>
  <system_app name="com.hihonor.lbs"/>
  <system_app name="com.android.bluetooth"/>
  <system_app name="com.android.captiveportallogin"/>
  <system_app name="com.hihonor.hiaction"/>
  <system_app name="com.android.hwmirror"/>
  <system_app name="com.hihonor.android.airsharing"/>
  <system_app name="com.hihonor.rcsserviceapplication"/>
  <system_app name="com.iflytek.speechsuite"/>
  <system_app name="com.hihonor.hnstartupguide"/>
  <system_app name="com.ironsource.appcloud.oobe.honor"/>
  <system_app name="com.android.cellbroadcastreceiver"/>
  <system_app name="com.hihonor.hwid"/>
  <system_app name="com.unionpay.tsmservice"/>
  <system_app name="com.hihonor.widget"/>
  <system_app name="com.android.partnerbrowsercustomizations.tmobile"/>
  <system_app name="com.hihonor.regservice"/>
  <system_app name="com.hihonor.mirrorlink"/>
  <system_app name="com.android.hotwordenrollment.okgoogle"/>
  <system_app name="com.google.android.apps.work.oobconfig"/>
  <system_app name="com.android.providers.userdictionary"/>
  <system_app name="com.hihonor.retail.assistant"/>
  <system_app name="com.hihonor.hnreader"/>
  <system_app name="com.hihonor.hiassistant"/>
  <system_app name="com.hihonor.vdrive"/>
  <system_app name="com.hihonor.android.extdisplay"/>
  <system_app name="com.hihonor.email"/>
  <system_app name="com.hihonor.contacts"/>
  <system_app name="com.hihonor.notepad"/>
  <system_app name="com.hihonor.calendar"/>
  <system_app name="com.android.permissioncontroller"/>
  <system_app name="com.hihonor.hwvoipservice"/>
  <system_app name="com.hihonor.contentsensor"/>
  <system_app name="com.hihonor.hicard"/>
  <system_app name="com.hihonor.hilink.framework"/>
  <system_app name="com.hihonor.himovie"/>
  <system_app name="com.hihonor.himovie.partner1"/>
  <system_app name="com.hihonor.himovie.partner2"/>
  <system_app name="com.hihonor.search"/>
  <system_app name="com.hihonor.recsys"/>
  <system_app name="com.hihonor.hiai"/>
  <system_app name="com.hihonor.pcassistant"/>
  <system_app name="com.hihonor.profile"/>
  <system_app name="com.hihonor.systemserver"/>
  <system_app name="com.hihonor.mycenter"/>
  <system_app name="com.hihonor.numberidentity"/>
  <system_app name="com.hihonor.pengine"/>
  <system_app name="com.hihonor.mmitest"/>
  <system_app name="com.hihonor.runningtestii"/>
  <system_app name="com.hihonor.android.rftest"/>
  <system_app name="com.hihonor.mmiautotest"/>
  <system_app name="com.hihonor.manufacture.wificonnect"/>
  <system_app name="com.hihonor.tplcdtest"/>
  <system_app name="com.hihonor.retaildemo"/>
  <system_app name="com.hihonor.assetsync"/>
  <system_app name="com.hihonor.printservice"/>
  <system_app name="com.hihonor.stylus.floatmenu"/>
  <system_app name="android.ext.services"/>
  <system_app name="com.hihonor.hicar"/>
  <system_app name="com.sohu.sohuvideo.emplayer"/>
  <system_app name="com.tencent.qqlivehonor"/>
  <system_app name="com.hihonor.dmsdp"/>
  <system_app name="com.android.simappdialog"/>
  <system_app name="com.hihonor.featurelayer.featureframework"/>
  <system_app name="com.hihonor.contacts.sync"/>
  <system_app name="com.hihonor.experience.lio"/>
  <system_app name="com.hihonor.vrmmitest"/>
  <system_app name="android"/>
  <system_app name="com.hihonor.scenepack"/>
  <system_app name="com.hihonor.secime"/>
  <system_app name="com.hihonor.photos"/>
  <system_app name="com.hihonor.hnockbar"/>
  <system_app name="com.hihonor.meetime"/>
  <system_app name="com.hihonor.controlcenter"/>
  <system_app name="com.hihonor.localBackup"/>
  <system_app name="com.hihonor.bonevoiceui"/>
  <system_app name="com.hihonor.featurelayer.sharedfeature.map"/>
  <system_app name="com.hihonor.educenter"/>
  <system_app name="com.hihonor.featurelayer.sharedfeature.stylus"/>
  <system_app name="com.hihonor.stylus.mpenzone"/>
  <system_app name="com.hihonor.magazine"/>
  <system_app name="com.hihonor.calculator"/>
  <system_app name="com.hihonor.mirror"/>
  <system_app name="com.android.providers.contacts"/>
  <system_app name="com.hihonor.soundrecorder"/>
  <system_app name="com.bjbyhd.screenreader_honor"/>
  <system_app name="com.hihonor.searchservice"/>
  <system_app name="com.hihonor.deskclock"/>
  <system_app name="com.hihonor.phone.recorder"/>
  <system_app name="com.hihonor.filemanager"/>
  <system_app name="com.hihonor.filemanager"/>
  <system_app name="com.hihonor.music"/>
  <system_app name="com.hihonor.privatespace"/>
  <system_app name="com.hihonor.gameassistant"/>
  <system_app name="com.hihonor.hbm"/>
  <system_app name="com.hihonor.smartshot"/>
  <system_app name="com.hihonor.ar.measure"/>
  <system_app name="com.hihonor.arengine.service"/>
  <system_app name="com.hihonor.audioaccessorymanager"/>
  <system_app name="com.hihonor.game.kitserver"/>
  <system_app name="com.hihonor.gameperceptio"/>
  <system_app name="com.hihonor.webview"/>
  <system_app name="com.hihonor.multimedia.audioengine"/>
  <system_app name="com.hihonor.behaviorauth"/>
  <system_app name="com.hihonor.hwblockchain"/>
  <system_app name="com.hihonor.coauthservice"/>
  <system_app name="com.hihonor.hwpanpayservice"/>
  <system_app name="com.hihonor.welinknow"/>
  <system_app name="com.android.stk"/>
  <system_app name="com.hihonor.dsdscardmanager"/>
  <system_app name="com.hihonor.featurelayer.sharedfeature.xrkit"/>
  <system_app name="com.hihonor.associateassistant"/>
  <system_app name="com.hihonor.security2"/>
  <system_app name="com.hihonor.hwddmp"/>
  <system_app name="com.hihonor.devicegroupmanage"/>
  <system_app name="com.hihonor.nearby"/>
  <system_app name="com.hihonor.android.FMRadio"/>
  <system_app name="cn.honor.qinxuan"/>
  <system_app name="com.hihonor.id"/>
  <system_app name="com.android.cellbroadcastreceiver.module"/>
  <system_app name="com.kugou.fanxing.honor"/>
  <system_app name="com.hihonor.gameperceptio"/>
  <system_app name="com.hihonor.fastapp"/>
  <system_app name="com.hihonor.suggestion"/>
  <system_app name="com.hihonor.aipluginengine"/>
  <system_app name="com.android.wifi.resources"/>
  <system_app name="com.android.providers.media.module"/>
  <system_app name="com.hihonor.iaware"/>
  <system_app name="com.hihonor.brain"/>
  <system_app name="com.hihonor.def"/>
  <system_app name="com.android.hotspot2.osulogin"/>
  <system_app name="com.hihonor.awareness"/>
  <system_app name="com.qualcomm.location"/>
  <system_app name="com.hihonor.assistant"/>
  <system_app name="com.dts.dtsxultra"/>
  <system_app name="com.hihonor.findmydevice"/>
  <system_app name="com.honor.sampleui"/>
  <system_app name="com.honor.trustcircle"/>
  <system_app name="com.hihonor.mirror"/>
  <system_app name="com.hihonor.hiviewpush"/>
  <system_app name="com.hihonor.hiboard"/>
  <system_app name="com.hihonor.servicecenter"/>
  <system_app name="com.hihonor.keychain"/>
</notchscreen_whitelist>